core/__init__.py
core/accuracy_enhancer.py
core/engine.py
core/search_engine.py
core/speed_optimizer.py
losearch-0.1.1.post1.dist-info/licenses/LICENSE
models/__init__.py
utils/__init__.py
utils/context_extractor.py
utils/text_processor.py
losearch-0.1.1.post1.dist-info/METADATA
losearch-0.1.1.post1.dist-info/WHEEL
losearch-0.1.1.post1.dist-info/top_level.txt
losearch-0.1.1.post1.dist-info/RECORD
