Metadata-Version: 2.4
Name: LoSearch
Version: 0.1.1.post1
Summary: A high-performance Python search library with intelligent relevance scoring, advanced indexing capabilities, and multilingual support for Persian and English.
Home-page: https://github.com/MadricTeam/LoSearch
Author: Madric
Author-email: madric.offical@gmail.com
Project-URL: Bug Reports, https://github.com/MadricTeam/LoSearch/issues
Project-URL: Source, https://github.com/MadricTeam/LoSearch
Project-URL: Documentation, https://github.com/MadricTeam/LoSearch/blob/main/LoSearch_Tutorial.md
Keywords: search,indexing,text-processing,multilingual,persian,farsi
Classifier: Development Status :: 4 - Beta
Classifier: Intended Audience :: Developers
Classifier: License :: OSI Approved :: MIT License
Classifier: Operating System :: OS Independent
Classifier: Programming Language :: Python :: 3
Classifier: Programming Language :: Python :: 3.7
Classifier: Programming Language :: Python :: 3.8
Classifier: Programming Language :: Python :: 3.9
Classifier: Programming Language :: Python :: 3.10
Classifier: Programming Language :: Python :: 3.11
Classifier: Topic :: Software Development :: Libraries :: Python Modules
Classifier: Topic :: Text Processing :: Indexing
Classifier: Topic :: Internet :: WWW/HTTP :: Indexing/Search
Requires-Python: >=3.7
License-File: LICENSE
Requires-Dist: build>=1.2.2
Requires-Dist: flask>=3.0.3
Requires-Dist: nltk>=3.9.1
Requires-Dist: redis>=6.1.1
Requires-Dist: scikit-learn>=1.3.2
Requires-Dist: sqlalchemy>=2.0.0
Dynamic: author
Dynamic: author-email
Dynamic: classifier
Dynamic: description
Dynamic: description-content-type
Dynamic: home-page
Dynamic: keywords
Dynamic: license-file
Dynamic: project-url
Dynamic: requires-dist
Dynamic: requires-python
Dynamic: summary
